synaptiq_datawarehouse/__init__.py
synaptiq_datawarehouse/integrations.py
synaptiq_datawarehouse/schemas.py
synaptiq_datawarehouse/config/prod.yaml
synaptiq_datawarehouse/tests/test_query_everhour.py
synaptiq_datawarehouse-0.1.11.dist-info/METADATA
synaptiq_datawarehouse-0.1.11.dist-info/WHEEL
synaptiq_datawarehouse-0.1.11.dist-info/RECORD
