Metadata-Version: 2.3
Name: synaptiq-datawarehouse
Version: 0.1.11
Summary: Add your description here
Requires-Python: >=3.9
Requires-Dist: google-api-python-client>=2.143.0
Requires-Dist: google-auth-httplib2>=0.2.0
Requires-Dist: google-auth-oauthlib>=1.2.1
Requires-Dist: google-auth>=2.34.0
Requires-Dist: google-cloud-bigquery>=3.25.0
Requires-Dist: pandas>=2.2.2
Requires-Dist: pyspark>=3.5.2
Requires-Dist: pyyaml>=6.0.2
Requires-Dist: requests>=2.32.3
Requires-Dist: xero-python>=6.3.0
